sayd/__init__.py
sayd/__main__.py
sayd/_client.py
sayd/_server.py
sayd/py.typed
sayd-1.2.9.dist-info/LICENSE
sayd-1.2.9.dist-info/METADATA
sayd-1.2.9.dist-info/NOTICE
sayd-1.2.9.dist-info/WHEEL
sayd-1.2.9.dist-info/entry_points.txt
sayd-1.2.9.dist-info/RECORD
