Metadata-Version: 2.1
Name: sayd
Version: 1.2.9
Summary: A performant asynchronous communication protocol in pure Python.
Home-page: https://github.com/lw016/sayd
License: Apache-2.0
Keywords: network,protocol,communication
Author: LW016
Requires-Python: >=3.8.0,<4.0.0
Classifier: Framework :: AsyncIO
Classifier: Intended Audience :: Developers
Classifier: License :: OSI Approved :: Apache Software License
Classifier: Operating System :: Android
Classifier: Operating System :: MacOS :: MacOS X
Classifier: Operating System :: Microsoft :: Windows
Classifier: Operating System :: POSIX :: Linux
Classifier: Operating System :: Unix
Classifier: Programming Language :: Python :: 3
Classifier: Programming Language :: Python :: 3.8
Classifier: Programming Language :: Python :: 3.9
Classifier: Programming Language :: Python :: 3.10
Classifier: Programming Language :: Python :: 3.11
Classifier: Programming Language :: Python :: 3.12
Classifier: Topic :: Internet
Classifier: Topic :: Software Development :: Libraries
Requires-Dist: pyOpenSSL (==24.1.0)
Requires-Dist: rich (==12.5.1)
Requires-Dist: typer (==0.4.1)
Requires-Dist: ujson (==5.6.0)
Requires-Dist: uvloop (==0.17.0)
Project-URL: Repository, https://github.com/lw016/sayd
